pyfood/__init__.py
pyfood/build_assets.py
pyfood/utils.py
pyfood/assets/nutri/nutrimap.json
pyfood/assets/nutri/sparse_nutriscores.npz
pyfood/assets/nutri/units.json
pyfood/assets/nutri/vnr.json
pyfood/assets/nutri/CIQUAL/CIQUAL_foodmap.json
pyfood/assets/nutri/CIQUAL/TableCiqual2017.csv
pyfood/assets/nutri/CIQUAL/TableCiqual2017_new.csv
pyfood/assets/seasons/sparse_seasons_Canada.npz
pyfood/assets/seasons/sparse_seasons_EU.npz
pyfood/assets/seasons/sparse_seasons_France.npz
pyfood/assets/seasons/sparse_seasons_Germany.npz
pyfood/assets/seasons/sparse_seasons_Israel.npz
pyfood/assets/seasons/sparse_seasons_Italy.npz
pyfood/assets/seasons/sparse_seasons_Japan.npz
pyfood/assets/seasons/sparse_seasons_Portugal.npz
pyfood/assets/seasons/sparse_seasons_Senegal.npz
pyfood/assets/seasons/sparse_seasons_Spain.npz
pyfood/assets/seasons/sparse_seasons_United Kingdom.npz
pyfood/assets/seasons/input/Canada/Canada_localseasonal.txt
pyfood/assets/seasons/input/Canada/Canada_permanent.txt
pyfood/assets/seasons/input/Canada/Canada_seasonal.txt
pyfood/assets/seasons/input/France/France_localseasonal.txt
pyfood/assets/seasons/input/France/France_permanent.txt
pyfood/assets/seasons/input/France/France_seasonal.txt
pyfood/assets/seasons/input/Germany/Germany_localseasonal.txt
pyfood/assets/seasons/input/Germany/Germany_permanent.txt
pyfood/assets/seasons/input/Israel/Israel_localseasonal.txt
pyfood/assets/seasons/input/Israel/Israel_permanent.txt
pyfood/assets/seasons/input/Israel/Israel_seasonal.txt
pyfood/assets/seasons/input/Italy/Italy_localseasonal.txt
pyfood/assets/seasons/input/Italy/Italy_permanent.txt
pyfood/assets/seasons/input/Japan/Japan_localseasonal.txt
pyfood/assets/seasons/input/Japan/Japan_permanent.txt
pyfood/assets/seasons/input/Portugal/Portugal_localseasonal.txt
pyfood/assets/seasons/input/Portugal/Portugal_permanent.txt
pyfood/assets/seasons/input/Senegal/Senegal_localseasonal.txt
pyfood/assets/seasons/input/Senegal/Senegal_permanent.txt
pyfood-0.0.5.dist-info/LICENSE
pyfood-0.0.5.dist-info/METADATA
pyfood-0.0.5.dist-info/WHEEL
pyfood-0.0.5.dist-info/top_level.txt
pyfood-0.0.5.dist-info/RECORD
