Metadata-Version: 2.1
Name: pyfood
Version: 0.0.5
Summary: Pyfood: A Python package to process food
Home-page: UNKNOWN
Author: Michel Deudon
Author-email: michel@local-seasonal.org
Maintainer: Local Seasonal
License: Creative Commons Attribution 4.0 International License.
Platform: UNKNOWN
Requires-Python: >=3.6
License-File: LICENSE
Requires-Dist: numpy
Requires-Dist: scikit-learn (>=0.20.1)
Requires-Dist: Unidecode (>=1.1.0)
